happyscript/__init__.py
happyscript/imglib.py
happyscript/inifile.py
happyscript/modulereader.py
happyscript/scriptartwork.py
happyscript/scriptcontrol.py
happyscript/scriptexceptions.py
happyscript/scriptgui.py
happyscript/scriptinfo.py
happyscript/scriptmanager.py
happyscript/scriptparams.py
happyscript/scriptreader.py
happyscript/scriptrunner.py
happyscript/staticscriptmanager.py
happyscript/testloghandler.py
happyscript/charts/__init__.py
happyscript/charts/chart.py
happyscript/charts/histogram_chart.py
happyscript/charts/histogram_series.py
happyscript/charts/matplotlib_chart.py
happyscript/charts/panel_charts.py
happyscript/charts/scatter_chart.py
happyscript/charts/scatter_series.py
happyscript/charts/time_chart.py
happyscript/charts/time_series.py
happyscript/forms/form_askchoice.py
happyscript/forms/form_askimage.py
happyscript/forms/form_main.py
happyscript/forms/form_ontestfailure.py
happyscript/forms/form_serials.py
happyscript/forms/form_settings.py
happyscript/forms/form_stop.py
happyscript/forms/formsbase.py
happyscript/panels/panel_log.py
happyscript/panels/panel_messages.py
happyscript/panels/panel_scripts2.py
happyscript/panels/panel_tests.py
happyscript/panels/panelsbase.py
happyscript/splashmenu/exit.png
happyscript/splashmenu/forms.py
happyscript/splashmenu/splashmenuform.py
happyscript/splashmenu/splashmenumain.py
happyscript/testlog/global_log_handler.py
happyscript/testlog/log_to_text.py
happyscript/testlog/logtoxml.py
happyscript/testlog/printredirect.py
happyscript/userpanel/userpanel.py
happyscript/userpanel/userpanelvalue.py
happyscript-0.0.49.dist-info/METADATA
happyscript-0.0.49.dist-info/WHEEL
happyscript-0.0.49.dist-info/top_level.txt
happyscript-0.0.49.dist-info/RECORD
