Metadata-Version: 2.4
Name: happyscript
Version: 0.0.49
Summary: Framework for running scripts
Requires-Python: >=3.5
Requires-Dist: wxpython
Requires-Dist: numpy
